ttvfast/__init__.py
ttvfast/_ttvfast.cpython-35m-darwin.so
ttvfast/models.py
ttvfast/version.py
ttvfast-0.3.0.dist-info/DESCRIPTION.rst
ttvfast-0.3.0.dist-info/METADATA
ttvfast-0.3.0.dist-info/RECORD
ttvfast-0.3.0.dist-info/WHEEL
ttvfast-0.3.0.dist-info/metadata.json
ttvfast-0.3.0.dist-info/top_level.txt
