Metadata-Version: 2.0
Name: ttvfast
Version: 0.3.0
Summary: Python wrapper to ttvfast
Home-page: https://github.com/mindriot101/ttvfast-python
Author: Simon Walker
Author-email: s.r.walker101@googlemail.com
License: GPL
Platform: UNKNOWN
Classifier: Development Status :: 3 - Alpha
Classifier: Intended Audience :: Science/Research
Classifier: License :: OSI Approved :: GNU General Public License v2 (GPLv2)
Classifier: Topic :: Scientific/Engineering :: Physics
Classifier: Programming Language :: Python :: 2
Classifier: Programming Language :: Python :: 2.6
Classifier: Programming Language :: Python :: 2.7
Classifier: Programming Language :: Python :: 3
Classifier: Programming Language :: Python :: 3.4
Classifier: Programming Language :: Python :: 3.5
